comliner/__init__.py
comliner/dummy.py
comliner-0.4.1.dist-info/METADATA
comliner-0.4.1.dist-info/WHEEL
comliner-0.4.1.dist-info/licenses/LICENSE.txt
comliner-0.4.1.dist-info/RECORD
