Metadata-Version: 2.1
Name: comliner
Version: 0.4.1
Summary: Command Line Interface Wrapper for Python Functions. Wrap your Python functions with a simple command line interface, so that they can be run directly from the command line, just like any shell command.  This is achieved by simply adding a decorator in front of the function and creating a small standardized executible script.
Project-URL: Source, https://github.com/proggy/comliner
Project-URL: Homepage, https://github.com/proggy/comliner
Project-URL: Bug Tracker, https://github.com/proggy/comliner/issues
Author-email: Daniel Jung <proggy-contact@mailbox.org>
Maintainer-email: Daniel Jung <proggy-contact@mailbox.org>
License-File: LICENSE.txt
Classifier: License :: OSI Approved :: GNU General Public License v2 (GPLv2)
Classifier: Operating System :: OS Independent
Classifier: Programming Language :: Python :: 3
Requires-Python: >=3.7
